environmentinator/__init__.py
environmentinator-0.1.5.dist-info/METADATA
environmentinator-0.1.5.dist-info/WHEEL
environmentinator-0.1.5.dist-info/RECORD
