Metadata-Version: 2.1
Name: environmentinator
Version: 0.1.5
Summary: Python library to ensure the runtime executing your code meets application requirements.
Author-email: Jeffrey McAteer <jeffrey-pydev@jmcateer.com>
